envguard/__init__.py
envguard/cli.py
envguard/validator.py
envguard-0.1.dist-info/METADATA
envguard-0.1.dist-info/WHEEL
envguard-0.1.dist-info/entry_points.txt
envguard-0.1.dist-info/top_level.txt
envguard-0.1.dist-info/RECORD
