Metadata-Version: 2.2
Name: EnvGuard
Version: 0.1
Summary: A tool to check for missing or incorrect environment variables in .env files.
Home-page: https://github.com/ktsoaela/EnvGuard
Author: Khotso Tsoaela
Author-email: khotso.s.tsoaela@gmail.com
Classifier: Programming Language :: Python :: 3
Classifier: License :: OSI Approved :: MIT License
Classifier: Operating System :: OS Independent
Requires-Dist: python-dotenv
Requires-Dist: click
Dynamic: author
Dynamic: author-email
Dynamic: classifier
Dynamic: description
Dynamic: description-content-type
Dynamic: home-page
Dynamic: requires-dist
Dynamic: summary
